cosmic_sdk/__init__.py
cosmic_sdk/connectors/__init__.py
cosmic_sdk/connectors/fathom/__init__.py
cosmic_sdk/connectors/fathom/models.py
cosmic_sdk/connectors/fathom/service.py
cosmic_sdk/connectors/posthog/__init__.py
cosmic_sdk/connectors/posthog/client.py
cosmic_sdk/connectors/posthog/models.py
cosmic_sdk/connectors/posthog/service.py
cosmic_sdk/connectors/pylon/__init__.py
cosmic_sdk/connectors/pylon/models.py
cosmic_sdk/connectors/pylon/service.py
cosmic_sdk/connectors/slack/__init__.py
cosmic_sdk/connectors/slack/models.py
cosmic_sdk/connectors/slack/provision_churn.csv
cosmic_sdk/connectors/slack/service.py
cosmic_sdk/connectors/slack/test.txt
cosmic_sdk/secrets/__init__.py
cosmic_sdk/secrets/aws.py
cosmic_sdk-0.3.28.dist-info/METADATA
cosmic_sdk-0.3.28.dist-info/WHEEL
cosmic_sdk-0.3.28.dist-info/licenses/LICENSE.md
cosmic_sdk-0.3.28.dist-info/RECORD
