Metadata-Version: 2.4
Name: cosmic_sdk
Version: 0.3.28
Summary: Collection of service connectors
Project-URL: Homepage, https://github.com/deepkalilabs/cosmic_sdk
Project-URL: Bug Tracker, https://github.com/deepkalilabs/cosmic_sdk/issues
Author-email: Charles Javelona <charlesjavelona@gmail.com>, Shikhar Sakhuja <shikharsakhuja@gmail.com>
License-File: LICENSE.md
Classifier: License :: OSI Approved :: MIT License
Classifier: Operating System :: OS Independent
Classifier: Programming Language :: Python :: 3
Requires-Python: >=3.7
Requires-Dist: boto3>=1.35.0
Requires-Dist: pydantic>=2.0.0
Requires-Dist: requests>=2.31.0
Requires-Dist: slack-sdk>=4.15.0
